tff/tff.v
module tff(
    input  wire clk,
    input  wire rst,
    input  wire t,
    output reg  q
);

always @(posedge clk) begin
    if (rst)
        q <= 1'b0;
    else if (t)
        q <= ~q;
    else
        q <= q;   // optional, can be omitted
end
initial begin

	$dumpfile("dump.vcd");
	$dumpvars(0,tff);
end
endmodule

tff/dump.vcd
$date
	Wed Jan 14 05:47:13 2026
$end
$version
	Icarus Verilog
$end
$timescale
	1ps
$end
$scope module tff $end
$var wire 1 ! clk $end
$var wire 1 " rst $end
$var wire 1 # t $end
$var reg 1 $ q $end
$upscope $end
$enddefinitions $end
$comment Show the parameter values. $end
$dumpall
$end
#0
$dumpvars
0$
z#
1"
1!
$end
#5000
0!
#10000
1!
#15000
0!
#20000
1!
#25000
0!
0"
#30000
0#
1!
#35000
0!
#40000
1!
#45000
0!
#50000
1!
#51000
1#
#55000
0!
#60000
1$
1!
#65000
0!
#70000
0$
1!
#75000
0!
#80000
1$
1!
#85000
0!
#90000
0$
1!
#95000
0!
#100000
1$
1!
#101000
0#
#105000
0!
#110000
1!
#115000
0!
#120000
1!
#121000
1#
#125000
0!
#130000
0$
1!
#131000
0#
#135000
0!
#140000
1!
#141000
1#
#145000
0!
#150000
1$
1!
#155000
0!
#160000
0$
1!
#165000
0!
#170000
1$
1!
#175000
0!
#180000
0$
1!
#181000
0#
#185000
0!
#190000
1!
#191000
1#
#195000
0!
#200000
1$
1!
#201000
0#
#205000
0!
#210000
1!
#211000
1#
#215000
0!
#220000
0$
1!
#221000
0#
