mux/mux.v
module mux(
  input [7:0] din,
  input [2:0] sel,
  output reg  dout
  );
  
  always@(*)
  begin
    case(sel)
    3'b000:dout = din[0];
    3'b001:dout = din[1];
    3'b010:dout = din[2];
    3'b011:dout = din[3];
    3'b100:dout = din[4];
    3'b101:dout = din[5];
    3'b110:dout = din[6];
    3'b111:dout = din[7];
    default: dout = 1'b0;
    endcase
  end
  
  
initial begin
$dumpfile("dump.vcd");
$dumpvars(1,mux);
end
 
 
 
endmodule

mux/dump.vcd
$date
	Tue Jan 13 04:53:39 2026
$end
$version
	Icarus Verilog
$end
$timescale
	1ps
$end
$scope module mux $end
$var wire 8 ! din [7:0] $end
$var wire 3 " sel [2:0] $end
$var reg 1 # dout $end
$upscope $end
$enddefinitions $end
$comment Show the parameter values. $end
$dumpall
$end
#0
$dumpvars
0#
b0 "
b0 !
$end
#1000
b1 "
#2000
b10 "
#3000
b11 "
#4000
b100 "
#5000
b101 "
#6000
b110 "
#7000
b111 "
#8000
1#
b0 "
b1 !
#9000
0#
b1 "
#10000
b10 "
#11000
b11 "
#12000
b100 "
#13000
b101 "
#14000
b110 "
#15000
b111 "
#16000
b0 "
b10 !
#17000
1#
b1 "
#18000
0#
b10 "
#19000
b11 "
#20000
b100 "
#21000
b101 "
#22000
b110 "
#23000
b111 "
#24000
1#
b0 "
b11 !
#25000
b1 "
#26000
0#
b10 "
#27000
b11 "
#28000
b100 "
#29000
b101 "
#30000
b110 "
#31000
b111 "
#32000
b0 "
b100 !
#33000
b1 "
#34000
1#
b10 "
#35000
0#
b11 "
#36000
b100 "
#37000
b101 "
#38000
b110 "
#39000
b111 "
#40000
1#
b0 "
b101 !
#41000
0#
b1 "
#42000
1#
b10 "
#43000
0#
b11 "
#44000
b100 "
#45000
b101 "
#46000
b110 "
#47000
b111 "
#48000
b0 "
b110 !
#49000
1#
b1 "
#50000
b10 "
#51000
0#
b11 "
#52000
b100 "
#53000
b101 "
#54000
b110 "
#55000
b111 "
#56000
1#
b0 "
b111 !
#57000
b1 "
#58000
b10 "
#59000
0#
b11 "
#60000
b100 "
#61000
b101 "
#62000
b110 "
#63000
b111 "
#64000
b0 "
b1000 !
#65000
b1 "
#66000
b10 "
#67000
1#
b11 "
#68000
0#
b100 "
#69000
b101 "
#70000
b110 "
#71000
b111 "
#72000
1#
b0 "
b1001 !
#73000
0#
b1 "
#74000
b10 "
#75000
1#
b11 "
#76000
0#
b100 "
#77000
b101 "
#78000
b110 "
#79000
b111 "
#80000
b0 "
b1010 !
#81000
1#
b1 "
#82000
0#
b10 "
#83000
1#
b11 "
#84000
0#
b100 "
#85000
b101 "
#86000
b110 "
#87000
b111 "
#88000
1#
b0 "
b1011 !
#89000
b1 "
#90000
0#
b10 "
#91000
1#
b11 "
#92000
0#
b100 "
#93000
b101 "
#94000
b110 "
#95000
b111 "
#96000
b0 "
b1100 !
#97000
b1 "
#98000
1#
b10 "
#99000
b11 "
#100000
0#
b100 "
#101000
b101 "
#102000
b110 "
#103000
b111 "
#104000
1#
b0 "
b1101 !
#105000
0#
b1 "
#106000
1#
b10 "
#107000
b11 "
#108000
0#
b100 "
#109000
b101 "
#110000
b110 "
#111000
b111 "
#112000
b0 "
b1110 !
#113000
1#
b1 "
#114000
b10 "
#115000
b11 "
#116000
0#
b100 "
#117000
b101 "
#118000
b110 "
#119000
b111 "
#120000
1#
b0 "
b1111 !
#121000
b1 "
#122000
b10 "
#123000
b11 "
#124000
0#
b100 "
#125000
b101 "
#126000
b110 "
#127000
b111 "
#128000
b0 "
b10000 !
#129000
b1 "
#130000
b10 "
#131000
b11 "
#132000
1#
b100 "
#133000
0#
b101 "
#134000
b110 "
#135000
b111 "
#136000
1#
b0 "
b10001 !
#137000
0#
b1 "
#138000
b10 "
#139000
b11 "
#140000
1#
b100 "
#141000
0#
b101 "
#142000
b110 "
#143000
b111 "
#144000
b0 "
b10010 !
#145000
1#
b1 "
#146000
0#
b10 "
#147000
b11 "
#148000
1#
b100 "
#149000
0#
b101 "
#150000
b110 "
#151000
b111 "
#152000
1#
b0 "
b10011 !
#153000
b1 "
#154000
0#
b10 "
#155000
b11 "
#156000
1#
b100 "
#157000
0#
b101 "
#158000
b110 "
#159000
b111 "
#160000
b0 "
b10100 !
#161000
b1 "
#162000
1#
b10 "
#163000
0#
b11 "
#164000
1#
b100 "
#165000
0#
b101 "
#166000
b110 "
#167000
b111 "
#168000
1#
b0 "
b10101 !
#169000
0#
b1 "
#170000
1#
b10 "
#171000
0#
b11 "
#172000
1#
b100 "
#173000
0#
b101 "
#174000
b110 "
#175000
b111 "
#176000
b0 "
b10110 !
#177000
1#
b1 "
#178000
b10 "
#179000
0#
b11 "
#180000
1#
b100 "
#181000
0#
b101 "
#182000
b110 "
#183000
b111 "
#184000
1#
b0 "
b10111 !
#185000
b1 "
#186000
b10 "
#187000
0#
b11 "
#188000
1#
b100 "
#189000
0#
b101 "
#190000
b110 "
#191000
b111 "
#192000
b0 "
b11000 !
#193000
b1 "
#194000
b10 "
#195000
1#
b11 "
#196000
b100 "
#197000
0#
b101 "
#198000
b110 "
#199000
b111 "
#200000
1#
b0 "
b11001 !
#201000
0#
b1 "
#202000
b10 "
#203000
1#
b11 "
#204000
b100 "
#205000
0#
b101 "
#206000
b110 "
#207000
b111 "
#208000
b0 "
b11010 !
#209000
1#
b1 "
#210000
0#
b10 "
#211000
1#
b11 "
#212000
b100 "
#213000
0#
b101 "
#214000
b110 "
#215000
b111 "
#216000
1#
b0 "
b11011 !
#217000
b1 "
#218000
0#
b10 "
#219000
1#
b11 "
#220000
b100 "
#221000
0#
b101 "
#222000
b110 "
#223000
b111 "
#224000
b0 "
b11100 !
#225000
b1 "
#226000
1#
b10 "
#227000
b11 "
#228000
b100 "
#229000
0#
b101 "
#230000
b110 "
#231000
b111 "
#232000
1#
b0 "
b11101 !
#233000
0#
b1 "
#234000
1#
b10 "
#235000
b11 "
#236000
b100 "
#237000
0#
b101 "
#238000
b110 "
#239000
b111 "
#240000
b0 "
b11110 !
#241000
1#
b1 "
#242000
b10 "
#243000
b11 "
#244000
b100 "
#245000
0#
b101 "
#246000
b110 "
#247000
b111 "
#248000
1#
b0 "
b11111 !
#249000
b1 "
#250000
b10 "
#251000
b11 "
#252000
b100 "
#253000
0#
b101 "
#254000
b110 "
#255000
b111 "
#256000
b0 "
b100000 !
#257000
b1 "
#258000
b10 "
#259000
b11 "
#260000
b100 "
#261000
1#
b101 "
#262000
0#
b110 "
#263000
b111 "
#264000
1#
b0 "
b100001 !
#265000
0#
b1 "
#266000
b10 "
#267000
b11 "
#268000
b100 "
#269000
1#
b101 "
#270000
0#
b110 "
#271000
b111 "
#272000
b0 "
b100010 !
#273000
1#
b1 "
#274000
0#
b10 "
#275000
b11 "
#276000
b100 "
#277000
1#
b101 "
#278000
0#
b110 "
#279000
b111 "
#280000
1#
b0 "
b100011 !
#281000
b1 "
#282000
0#
b10 "
#283000
b11 "
#284000
b100 "
#285000
1#
b101 "
#286000
0#
b110 "
#287000
b111 "
#288000
b0 "
b100100 !
#289000
b1 "
#290000
1#
b10 "
#291000
0#
b11 "
#292000
b100 "
#293000
1#
b101 "
#294000
0#
b110 "
#295000
b111 "
#296000
1#
b0 "
b100101 !
#297000
0#
b1 "
#298000
1#
b10 "
#299000
0#
b11 "
#300000
b100 "
#301000
1#
b101 "
#302000
0#
b110 "
#303000
b111 "
#304000
b0 "
b100110 !
#305000
1#
b1 "
#306000
b10 "
#307000
0#
b11 "
#308000
b100 "
#309000
1#
b101 "
#310000
0#
b110 "
#311000
b111 "
#312000
1#
b0 "
b100111 !
#313000
b1 "
#314000
b10 "
#315000
0#
b11 "
#316000
b100 "
#317000
1#
b101 "
#318000
0#
b110 "
#319000
b111 "
#320000
b0 "
b101000 !
#321000
b1 "
#322000
b10 "
#323000
1#
b11 "
#324000
0#
b100 "
#325000
1#
b101 "
#326000
0#
b110 "
#327000
b111 "
#328000
1#
b0 "
b101001 !
#329000
0#
b1 "
#330000
b10 "
#331000
1#
b11 "
#332000
0#
b100 "
#333000
1#
b101 "
#334000
0#
b110 "
#335000
b111 "
#336000
b0 "
b101010 !
#337000
1#
b1 "
#338000
0#
b10 "
#339000
1#
b11 "
#340000
0#
b100 "
#341000
1#
b101 "
#342000
0#
b110 "
#343000
b111 "
#344000
1#
b0 "
b101011 !
#345000
b1 "
#346000
0#
b10 "
#347000
1#
b11 "
#348000
0#
b100 "
#349000
1#
b101 "
#350000
0#
b110 "
#351000
b111 "
#352000
b0 "
b101100 !
#353000
b1 "
#354000
1#
b10 "
#355000
b11 "
#356000
0#
b100 "
#357000
1#
b101 "
#358000
0#
b110 "
#359000
b111 "
#360000
1#
b0 "
b101101 !
#361000
0#
b1 "
#362000
1#
b10 "
#363000
b11 "
#364000
0#
b100 "
#365000
1#
b101 "
#366000
0#
b110 "
#367000
b111 "
#368000
b0 "
b101110 !
#369000
1#
b1 "
#370000
b10 "
#371000
b11 "
#372000
0#
b100 "
#373000
1#
b101 "
#374000
0#
b110 "
#375000
b111 "
#376000
1#
b0 "
b101111 !
#377000
b1 "
#378000
b10 "
#379000
b11 "
#380000
0#
b100 "
#381000
1#
b101 "
#382000
0#
b110 "
#383000
b111 "
#384000
b0 "
b110000 !
#385000
b1 "
#386000
b10 "
#387000
b11 "
#388000
1#
b100 "
#389000
b101 "
#390000
0#
b110 "
#391000
b111 "
#392000
1#
b0 "
b110001 !
#393000
0#
b1 "
#394000
b10 "
#395000
b11 "
#396000
1#
b100 "
#397000
b101 "
#398000
0#
b110 "
#399000
b111 "
#400000
b0 "
b110010 !
#401000
1#
b1 "
#402000
0#
b10 "
#403000
b11 "
#404000
1#
b100 "
#405000
b101 "
#406000
0#
b110 "
#407000
b111 "
#408000
1#
b0 "
b110011 !
#409000
b1 "
#410000
0#
b10 "
#411000
b11 "
#412000
1#
b100 "
#413000
b101 "
#414000
0#
b110 "
#415000
b111 "
#416000
b0 "
b110100 !
#417000
b1 "
#418000
1#
b10 "
#419000
0#
b11 "
#420000
1#
b100 "
#421000
b101 "
#422000
0#
b110 "
#423000
b111 "
#424000
1#
b0 "
b110101 !
#425000
0#
b1 "
#426000
1#
b10 "
#427000
0#
b11 "
#428000
1#
b100 "
#429000
b101 "
#430000
0#
b110 "
#431000
b111 "
#432000
b0 "
b110110 !
#433000
1#
b1 "
#434000
b10 "
#435000
0#
b11 "
#436000
1#
b100 "
#437000
b101 "
#438000
0#
b110 "
#439000
b111 "
#440000
1#
b0 "
b110111 !
#441000
b1 "
#442000
b10 "
#443000
0#
b11 "
#444000
1#
b100 "
#445000
b101 "
#446000
0#
b110 "
#447000
b111 "
#448000
b0 "
b111000 !
#449000
b1 "
#450000
b10 "
#451000
1#
b11 "
#452000
b100 "
#453000
b101 "
#454000
0#
b110 "
#455000
b111 "
#456000
1#
b0 "
b111001 !
#457000
0#
b1 "
#458000
b10 "
#459000
1#
b11 "
#460000
b100 "
#461000
b101 "
#462000
0#
b110 "
#463000
b111 "
#464000
b0 "
b111010 !
#465000
1#
b1 "
#466000
0#
b10 "
#467000
1#
b11 "
#468000
b100 "
#469000
b101 "
#470000
0#
b110 "
#471000
b111 "
#472000
1#
b0 "
b111011 !
#473000
b1 "
#474000
0#
b10 "
#475000
1#
b11 "
#476000
b100 "
#477000
b101 "
#478000
0#
b110 "
#479000
b111 "
#480000
b0 "
b111100 !
#481000
b1 "
#482000
1#
b10 "
#483000
b11 "
#484000
b100 "
#485000
b101 "
#486000
0#
b110 "
#487000
b111 "
#488000
1#
b0 "
b111101 !
#489000
0#
b1 "
#490000
1#
b10 "
#491000
b11 "
#492000
b100 "
#493000
b101 "
#494000
0#
b110 "
#495000
b111 "
#496000
b0 "
b111110 !
#497000
1#
b1 "
#498000
b10 "
#499000
b11 "
#500000
b100 "
#501000
b101 "
#502000
0#
b110 "
#503000
b111 "
#504000
1#
b0 "
b111111 !
#505000
b1 "
#506000
b10 "
#507000
b11 "
#508000
b100 "
#509000
b101 "
#510000
0#
b110 "
#511000
b111 "
#512000
b0 "
b1000000 !
#513000
b1 "
#514000
b10 "
#515000
b11 "
#516000
b100 "
#517000
b101 "
#518000
1#
b110 "
#519000
0#
b111 "
#520000
1#
b0 "
b1000001 !
#521000
0#
b1 "
#522000
b10 "
#523000
b11 "
#524000
b100 "
#525000
b101 "
#526000
1#
b110 "
#527000
0#
b111 "
#528000
b0 "
b1000010 !
#529000
1#
b1 "
#530000
0#
b10 "
#531000
b11 "
#532000
b100 "
#533000
b101 "
#534000
1#
b110 "
#535000
0#
b111 "
#536000
1#
b0 "
b1000011 !
#537000
b1 "
#538000
0#
b10 "
#539000
b11 "
#540000
b100 "
#541000
b101 "
#542000
1#
b110 "
#543000
0#
b111 "
#544000
b0 "
b1000100 !
#545000
b1 "
#546000
1#
b10 "
#547000
0#
b11 "
#548000
b100 "
#549000
b101 "
#550000
1#
b110 "
#551000
0#
b111 "
#552000
1#
b0 "
b1000101 !
#553000
0#
b1 "
#554000
1#
b10 "
#555000
0#
b11 "
#556000
b100 "
#557000
b101 "
#558000
1#
b110 "
#559000
0#
b111 "
#560000
b0 "
b1000110 !
#561000
1#
b1 "
#562000
b10 "
#563000
0#
b11 "
#564000
b100 "
#565000
b101 "
#566000
1#
b110 "
#567000
0#
b111 "
#568000
1#
b0 "
b1000111 !
#569000
b1 "
#570000
b10 "
#571000
0#
b11 "
#572000
b100 "
#573000
b101 "
#574000
1#
b110 "
#575000
0#
b111 "
#576000
b0 "
b1001000 !
#577000
b1 "
#578000
b10 "
#579000
1#
b11 "
#580000
0#
b100 "
#581000
b101 "
#582000
1#
b110 "
#583000
0#
b111 "
#584000
1#
b0 "
b1001001 !
#585000
0#
b1 "
#586000
b10 "
#587000
1#
b11 "
#588000
0#
b100 "
#589000
b101 "
#590000
1#
b110 "
#591000
0#
b111 "
#592000
b0 "
b1001010 !
#593000
1#
b1 "
#594000
0#
b10 "
#595000
1#
b11 "
#596000
0#
b100 "
#597000
b101 "
#598000
1#
b110 "
#599000
0#
b111 "
#600000
1#
b0 "
b1001011 !
#601000
b1 "
#602000
0#
b10 "
#603000
1#
b11 "
#604000
0#
b100 "
#605000
b101 "
#606000
1#
b110 "
#607000
0#
b111 "
#608000
b0 "
b1001100 !
#609000
b1 "
#610000
1#
b10 "
#611000
b11 "
#612000
0#
b100 "
#613000
b101 "
#614000
1#
b110 "
#615000
0#
b111 "
#616000
1#
b0 "
b1001101 !
#617000
0#
b1 "
#618000
1#
b10 "
#619000
b11 "
#620000
0#
b100 "
#621000
b101 "
#622000
1#
b110 "
#623000
0#
b111 "
#624000
b0 "
b1001110 !
#625000
1#
b1 "
#626000
b10 "
#627000
b11 "
#628000
0#
b100 "
#629000
b101 "
#630000
1#
b110 "
#631000
0#
b111 "
#632000
1#
b0 "
b1001111 !
#633000
b1 "
#634000
b10 "
#635000
b11 "
#636000
0#
b100 "
#637000
b101 "
#638000
1#
b110 "
#639000
0#
b111 "
#640000
b0 "
b1010000 !
#641000
b1 "
#642000
b10 "
#643000
b11 "
#644000
1#
b100 "
#645000
0#
b101 "
#646000
1#
b110 "
#647000
0#
b111 "
#648000
1#
b0 "
b1010001 !
#649000
0#
b1 "
#650000
b10 "
#651000
b11 "
#652000
1#
b100 "
#653000
0#
b101 "
#654000
1#
b110 "
#655000
0#
b111 "
#656000
b0 "
b1010010 !
#657000
1#
b1 "
#658000
0#
b10 "
#659000
b11 "
#660000
1#
b100 "
#661000
0#
b101 "
#662000
1#
b110 "
#663000
0#
b111 "
#664000
1#
b0 "
b1010011 !
#665000
b1 "
#666000
0#
b10 "
#667000
b11 "
#668000
1#
b100 "
#669000
0#
b101 "
#670000
1#
b110 "
#671000
0#
b111 "
#672000
b0 "
b1010100 !
#673000
b1 "
#674000
1#
b10 "
#675000
0#
b11 "
#676000
1#
b100 "
#677000
0#
b101 "
#678000
1#
b110 "
#679000
0#
b111 "
#680000
1#
b0 "
b1010101 !
#681000
0#
b1 "
#682000
1#
b10 "
#683000
0#
b11 "
#684000
1#
b100 "
#685000
0#
b101 "
#686000
1#
b110 "
#687000
0#
b111 "
#688000
b0 "
b1010110 !
#689000
1#
b1 "
#690000
b10 "
#691000
0#
b11 "
#692000
1#
b100 "
#693000
0#
b101 "
#694000
1#
b110 "
#695000
0#
b111 "
#696000
1#
b0 "
b1010111 !
#697000
b1 "
#698000
b10 "
#699000
0#
b11 "
#700000
1#
b100 "
#701000
0#
b101 "
#702000
1#
b110 "
#703000
0#
b111 "
#704000
b0 "
b1011000 !
#705000
b1 "
#706000
b10 "
#707000
1#
b11 "
#708000
b100 "
#709000
0#
b101 "
#710000
1#
b110 "
#711000
0#
b111 "
#712000
1#
b0 "
b1011001 !
#713000
0#
b1 "
#714000
b10 "
#715000
1#
b11 "
#716000
b100 "
#717000
0#
b101 "
#718000
1#
b110 "
#719000
0#
b111 "
#720000
b0 "
b1011010 !
#721000
1#
b1 "
#722000
0#
b10 "
#723000
1#
b11 "
#724000
b100 "
#725000
0#
b101 "
#726000
1#
b110 "
#727000
0#
b111 "
#728000
1#
b0 "
b1011011 !
#729000
b1 "
#730000
0#
b10 "
#731000
1#
b11 "
#732000
b100 "
#733000
0#
b101 "
#734000
1#
b110 "
#735000
0#
b111 "
#736000
b0 "
b1011100 !
#737000
b1 "
#738000
1#
b10 "
#739000
b11 "
#740000
b100 "
#741000
0#
b101 "
#742000
1#
b110 "
#743000
0#
b111 "
#744000
1#
b0 "
b1011101 !
#745000
0#
b1 "
#746000
1#
b10 "
#747000
b11 "
#748000
b100 "
#749000
0#
b101 "
#750000
1#
b110 "
#751000
0#
b111 "
#752000
b0 "
b1011110 !
#753000
1#
b1 "
#754000
b10 "
#755000
b11 "
#756000
b100 "
#757000
0#
b101 "
#758000
1#
b110 "
#759000
0#
b111 "
#760000
1#
b0 "
b1011111 !
#761000
b1 "
#762000
b10 "
#763000
b11 "
#764000
b100 "
#765000
0#
b101 "
#766000
1#
b110 "
#767000
0#
b111 "
#768000
b0 "
b1100000 !
#769000
b1 "
#770000
b10 "
#771000
b11 "
#772000
b100 "
#773000
1#
b101 "
#774000
b110 "
#775000
0#
b111 "
#776000
1#
b0 "
b1100001 !
#777000
0#
b1 "
#778000
b10 "
#779000
b11 "
#780000
b100 "
#781000
1#
b101 "
#782000
b110 "
#783000
0#
b111 "
#784000
b0 "
b1100010 !
#785000
1#
b1 "
#786000
0#
b10 "
#787000
b11 "
#788000
b100 "
#789000
1#
b101 "
#790000
b110 "
#791000
0#
b111 "
#792000
1#
b0 "
b1100011 !
#793000
b1 "
#794000
0#
b10 "
#795000
b11 "
#796000
b100 "
#797000
1#
b101 "
#798000
b110 "
#799000
0#
b111 "
#800000
b0 "
b1100100 !
#801000
b1 "
#802000
1#
b10 "
#803000
0#
b11 "
#804000
b100 "
#805000
1#
b101 "
#806000
b110 "
#807000
0#
b111 "
#808000
1#
b0 "
b1100101 !
#809000
0#
b1 "
#810000
1#
b10 "
#811000
0#
b11 "
#812000
b100 "
#813000
1#
b101 "
#814000
b110 "
#815000
0#
b111 "
#816000
b0 "
b1100110 !
#817000
1#
b1 "
#818000
b10 "
#819000
0#
b11 "
#820000
b100 "
#821000
1#
b101 "
#822000
b110 "
#823000
0#
b111 "
#824000
1#
b0 "
b1100111 !
#825000
b1 "
#826000
b10 "
#827000
0#
b11 "
#828000
b100 "
#829000
1#
b101 "
#830000
b110 "
#831000
0#
b111 "
#832000
b0 "
b1101000 !
#833000
b1 "
#834000
b10 "
#835000
1#
b11 "
#836000
0#
b100 "
#837000
1#
b101 "
#838000
b110 "
#839000
0#
b111 "
#840000
1#
b0 "
b1101001 !
#841000
0#
b1 "
#842000
b10 "
#843000
1#
b11 "
#844000
0#
b100 "
#845000
1#
b101 "
#846000
b110 "
#847000
0#
b111 "
#848000
b0 "
b1101010 !
#849000
1#
b1 "
#850000
0#
b10 "
#851000
1#
b11 "
#852000
0#
b100 "
#853000
1#
b101 "
#854000
b110 "
#855000
0#
b111 "
#856000
1#
b0 "
b1101011 !
#857000
b1 "
#858000
0#
b10 "
#859000
1#
b11 "
#860000
0#
b100 "
#861000
1#
b101 "
#862000
b110 "
#863000
0#
b111 "
#864000
b0 "
b1101100 !
#865000
b1 "
#866000
1#
b10 "
#867000
b11 "
#868000
0#
b100 "
#869000
1#
b101 "
#870000
b110 "
#871000
0#
b111 "
#872000
1#
b0 "
b1101101 !
#873000
0#
b1 "
#874000
1#
b10 "
#875000
b11 "
#876000
0#
b100 "
#877000
1#
b101 "
#878000
b110 "
#879000
0#
b111 "
#880000
b0 "
b1101110 !
#881000
1#
b1 "
#882000
b10 "
#883000
b11 "
#884000
0#
b100 "
#885000
1#
b101 "
#886000
b110 "
#887000
0#
b111 "
#888000
1#
b0 "
b1101111 !
#889000
b1 "
#890000
b10 "
#891000
b11 "
#892000
0#
b100 "
#893000
1#
b101 "
#894000
b110 "
#895000
0#
b111 "
#896000
b0 "
b1110000 !
#897000
b1 "
#898000
b10 "
#899000
b11 "
#900000
1#
b100 "
#901000
b101 "
#902000
b110 "
#903000
0#
b111 "
#904000
1#
b0 "
b1110001 !
#905000
0#
b1 "
#906000
b10 "
#907000
b11 "
#908000
1#
b100 "
#909000
b101 "
#910000
b110 "
#911000
0#
b111 "
#912000
b0 "
b1110010 !
#913000
1#
b1 "
#914000
0#
b10 "
#915000
b11 "
#916000
1#
b100 "
#917000
b101 "
#918000
b110 "
#919000
0#
b111 "
#920000
1#
b0 "
b1110011 !
#921000
b1 "
#922000
0#
b10 "
#923000
b11 "
#924000
1#
b100 "
#925000
b101 "
#926000
b110 "
#927000
0#
b111 "
#928000
b0 "
b1110100 !
#929000
b1 "
#930000
1#
b10 "
#931000
0#
b11 "
#932000
1#
b100 "
#933000
b101 "
#934000
b110 "
#935000
0#
b111 "
#936000
1#
b0 "
b1110101 !
#937000
0#
b1 "
#938000
1#
b10 "
#939000
0#
b11 "
#940000
1#
b100 "
#941000
b101 "
#942000
b110 "
#943000
0#
b111 "
#944000
b0 "
b1110110 !
#945000
1#
b1 "
#946000
b10 "
#947000
0#
b11 "
#948000
1#
b100 "
#949000
b101 "
#950000
b110 "
#951000
0#
b111 "
#952000
1#
b0 "
b1110111 !
#953000
b1 "
#954000
b10 "
#955000
0#
b11 "
#956000
1#
b100 "
#957000
b101 "
#958000
b110 "
#959000
0#
b111 "
#960000
b0 "
b1111000 !
#961000
b1 "
#962000
b10 "
#963000
1#
b11 "
#964000
b100 "
#965000
b101 "
#966000
b110 "
#967000
0#
b111 "
#968000
1#
b0 "
b1111001 !
#969000
0#
b1 "
#970000
b10 "
#971000
1#
b11 "
#972000
b100 "
#973000
b101 "
#974000
b110 "
#975000
0#
b111 "
#976000
b0 "
b1111010 !
#977000
1#
b1 "
#978000
0#
b10 "
#979000
1#
b11 "
#980000
b100 "
#981000
b101 "
#982000
b110 "
#983000
0#
b111 "
#984000
1#
b0 "
b1111011 !
#985000
b1 "
#986000
0#
b10 "
#987000
1#
b11 "
#988000
b100 "
#989000
b101 "
#990000
b110 "
#991000
0#
b111 "
#992000
b0 "
b1111100 !
#993000
b1 "
#994000
1#
b10 "
#995000
b11 "
#996000
b100 "
#997000
b101 "
#998000
b110 "
#999000
0#
b111 "
#1000000
1#
b0 "
b1111101 !
#1001000
0#
b1 "
#1002000
1#
b10 "
#1003000
b11 "
#1004000
b100 "
#1005000
b101 "
#1006000
b110 "
#1007000
0#
b111 "
#1008000
b0 "
b1111110 !
#1009000
1#
b1 "
#1010000
b10 "
#1011000
b11 "
#1012000
b100 "
#1013000
b101 "
#1014000
b110 "
#1015000
0#
b111 "
#1016000
1#
b0 "
b1111111 !
#1017000
b1 "
#1018000
b10 "
#1019000
b11 "
#1020000
b100 "
#1021000
b101 "
#1022000
b110 "
#1023000
0#
b111 "
#1024000
b0 "
b10000000 !
#1025000
b1 "
#1026000
b10 "
#1027000
b11 "
#1028000
b100 "
#1029000
b101 "
#1030000
b110 "
#1031000
1#
b111 "
#1032000
b0 "
b10000001 !
#1033000
0#
b1 "
#1034000
b10 "
#1035000
b11 "
#1036000
b100 "
#1037000
b101 "
#1038000
b110 "
#1039000
1#
b111 "
#1040000
0#
b0 "
b10000010 !
#1041000
1#
b1 "
#1042000
0#
b10 "
#1043000
b11 "
#1044000
b100 "
#1045000
b101 "
#1046000
b110 "
#1047000
1#
b111 "
#1048000
b0 "
b10000011 !
#1049000
b1 "
#1050000
0#
b10 "
#1051000
b11 "
#1052000
b100 "
#1053000
b101 "
#1054000
b110 "
#1055000
1#
b111 "
#1056000
0#
b0 "
b10000100 !
#1057000
b1 "
#1058000
1#
b10 "
#1059000
0#
b11 "
#1060000
b100 "
#1061000
b101 "
#1062000
b110 "
#1063000
1#
b111 "
#1064000
b0 "
b10000101 !
#1065000
0#
b1 "
#1066000
1#
b10 "
#1067000
0#
b11 "
#1068000
b100 "
#1069000
b101 "
#1070000
b110 "
#1071000
1#
b111 "
#1072000
0#
b0 "
b10000110 !
#1073000
1#
b1 "
#1074000
b10 "
#1075000
0#
b11 "
#1076000
b100 "
#1077000
b101 "
#1078000
b110 "
#1079000
1#
b111 "
#1080000
b0 "
b10000111 !
#1081000
b1 "
#1082000
b10 "
#1083000
0#
b11 "
#1084000
b100 "
#1085000
b101 "
#1086000
b110 "
#1087000
1#
b111 "
#1088000
0#
b0 "
b10001000 !
#1089000
b1 "
#1090000
b10 "
#1091000
1#
b11 "
#1092000
0#
b100 "
#1093000
b101 "
#1094000
b110 "
#1095000
1#
b111 "
#1096000
b0 "
b10001001 !
#1097000
0#
b1 "
#1098000
b10 "
#1099000
1#
b11 "
#1100000
0#
b100 "
#1101000
b101 "
#1102000
b110 "
#1103000
1#
b111 "
#1104000
0#
b0 "
b10001010 !
#1105000
1#
b1 "
#1106000
0#
b10 "
#1107000
1#
b11 "
#1108000
0#
b100 "
#1109000
b101 "
#1110000
b110 "
#1111000
1#
b111 "
#1112000
b0 "
b10001011 !
#1113000
b1 "
#1114000
0#
b10 "
#1115000
1#
b11 "
#1116000
0#
b100 "
#1117000
b101 "
#1118000
b110 "
#1119000
1#
b111 "
#1120000
0#
b0 "
b10001100 !
#1121000
b1 "
#1122000
1#
b10 "
#1123000
b11 "
#1124000
0#
b100 "
#1125000
b101 "
#1126000
b110 "
#1127000
1#
b111 "
#1128000
b0 "
b10001101 !
#1129000
0#
b1 "
#1130000
1#
b10 "
#1131000
b11 "
#1132000
0#
b100 "
#1133000
b101 "
#1134000
b110 "
#1135000
1#
b111 "
#1136000
0#
b0 "
b10001110 !
#1137000
1#
b1 "
#1138000
b10 "
#1139000
b11 "
#1140000
0#
b100 "
#1141000
b101 "
#1142000
b110 "
#1143000
1#
b111 "
#1144000
b0 "
b10001111 !
#1145000
b1 "
#1146000
b10 "
#1147000
b11 "
#1148000
0#
b100 "
#1149000
b101 "
#1150000
b110 "
#1151000
1#
b111 "
#1152000
0#
b0 "
b10010000 !
#1153000
b1 "
#1154000
b10 "
#1155000
b11 "
#1156000
1#
b100 "
#1157000
0#
b101 "
#1158000
b110 "
#1159000
1#
b111 "
#1160000
b0 "
b10010001 !
#1161000
0#
b1 "
#1162000
b10 "
#1163000
b11 "
#1164000
1#
b100 "
#1165000
0#
b101 "
#1166000
b110 "
#1167000
1#
b111 "
#1168000
0#
b0 "
b10010010 !
#1169000
1#
b1 "
#1170000
0#
b10 "
#1171000
b11 "
#1172000
1#
b100 "
#1173000
0#
b101 "
#1174000
b110 "
#1175000
1#
b111 "
#1176000
b0 "
b10010011 !
#1177000
b1 "
#1178000
0#
b10 "
#1179000
b11 "
#1180000
1#
b100 "
#1181000
0#
b101 "
#1182000
b110 "
#1183000
1#
b111 "
#1184000
0#
b0 "
b10010100 !
#1185000
b1 "
#1186000
1#
b10 "
#1187000
0#
b11 "
#1188000
1#
b100 "
#1189000
0#
b101 "
#1190000
b110 "
#1191000
1#
b111 "
#1192000
b0 "
b10010101 !
#1193000
0#
b1 "
#1194000
1#
b10 "
#1195000
0#
b11 "
#1196000
1#
b100 "
#1197000
0#
b101 "
#1198000
b110 "
#1199000
1#
b111 "
#1200000
0#
b0 "
b10010110 !
#1201000
1#
b1 "
#1202000
b10 "
#1203000
0#
b11 "
#1204000
1#
b100 "
#1205000
0#
b101 "
#1206000
b110 "
#1207000
1#
b111 "
#1208000
b0 "
b10010111 !
#1209000
b1 "
#1210000
b10 "
#1211000
0#
b11 "
#1212000
1#
b100 "
#1213000
0#
b101 "
#1214000
b110 "
#1215000
1#
b111 "
#1216000
0#
b0 "
b10011000 !
#1217000
b1 "
#1218000
b10 "
#1219000
1#
b11 "
#1220000
b100 "
#1221000
0#
b101 "
#1222000
b110 "
#1223000
1#
b111 "
#1224000
b0 "
b10011001 !
#1225000
0#
b1 "
#1226000
b10 "
#1227000
1#
b11 "
#1228000
b100 "
#1229000
0#
b101 "
#1230000
b110 "
#1231000
1#
b111 "
#1232000
0#
b0 "
b10011010 !
#1233000
1#
b1 "
#1234000
0#
b10 "
#1235000
1#
b11 "
#1236000
b100 "
#1237000
0#
b101 "
#1238000
b110 "
#1239000
1#
b111 "
#1240000
b0 "
b10011011 !
#1241000
b1 "
#1242000
0#
b10 "
#1243000
1#
b11 "
#1244000
b100 "
#1245000
0#
b101 "
#1246000
b110 "
#1247000
1#
b111 "
#1248000
0#
b0 "
b10011100 !
#1249000
b1 "
#1250000
1#
b10 "
#1251000
b11 "
#1252000
b100 "
#1253000
0#
b101 "
#1254000
b110 "
#1255000
1#
b111 "
#1256000
b0 "
b10011101 !
#1257000
0#
b1 "
#1258000
1#
b10 "
#1259000
b11 "
#1260000
b100 "
#1261000
0#
b101 "
#1262000
b110 "
#1263000
1#
b111 "
