demux/demux.v
module demux(
    input  wire        din,
    input  wire [2:0]  sel,
    output reg  [7:0]  dout
);

always @(*) begin
    dout = 8'b00000000;     // default: all outputs 0
    dout[sel] = din;        // route input to selected output
end

initial begin

        $dumpfile("dump.vcd");
        $dumpvars(0,demux);
end

endmodule

demux/dump.vcd
$date
	Wed Jan 14 05:12:15 2026
$end
$version
	Icarus Verilog
$end
$timescale
	1ps
$end
$scope module demux $end
$var wire 1 ! din $end
$var wire 3 " sel [2:0] $end
$var reg 8 # dout [7:0] $end
$upscope $end
$enddefinitions $end
$comment Show the parameter values. $end
$dumpall
$end
#0
$dumpvars
b0 #
b0 "
0!
$end
#1000
b1 "
#2000
b10 "
#3000
b11 "
#4000
b100 "
#5000
b101 "
#6000
b110 "
#7000
b111 "
#8000
b1 #
b0 "
1!
#9000
b10 #
b1 "
#10000
b100 #
b10 "
#11000
b1000 #
b11 "
#12000
b10000 #
b100 "
#13000
b100000 #
b101 "
#14000
b1000000 #
b110 "
#15000
b10000000 #
b111 "
